fast_bfmatcher/__init__.py
fast_bfmatcher/matching_ops.cpython-37m-x86_64-linux-gnu.so
fast_bfmatcher/matchers.py
fast_bfmatcher/utils.py
fast_bfmatcher/matching_ops.c
fast_bfmatcher/matching_ops.pyx
fast_bfmatcher/fast_ops.c
fast_bfmatcher/fast_ops.h
fast_bfmatcher/benchmark.py
fast_bfmatcher/extra/__init__.py
fast_bfmatcher/extra/tf.py
fast_bfmatcher/extra/cv.py
fast_bfmatcher/extra/np.py
fast_bfmatcher-1.5.0.dist-info/RECORD
fast_bfmatcher-1.5.0.dist-info/LICENSE
fast_bfmatcher-1.5.0.dist-info/METADATA
fast_bfmatcher-1.5.0.dist-info/top_level.txt
fast_bfmatcher-1.5.0.dist-info/WHEEL
fast_bfmatcher.libs/libgomp-b6de5f8b.so.1.0.0
