Metadata-Version: 2.1
Name: fast-bfmatcher
Version: 1.5.0
Summary: Faster implementation of OpenCV BFMatcher matcher
Home-page: https://github.com/kmkolasinski/fast-bfmatcher
Author: Krzysztof Kolasinski
Author-email: kmkolasinski@gmail.com
License: MIT
Platform: UNKNOWN
License-File: LICENSE
Requires-Dist: numpy (>=1.16.0)
